rahul_poetrypypi/__init__.py
rahul_poetrypypi-0.1.0.dist-info/WHEEL
rahul_poetrypypi-0.1.0.dist-info/METADATA
rahul_poetrypypi-0.1.0.dist-info/RECORD
