Metadata-Version: 2.1
Name: rahul-poetrypypi
Version: 0.1.0
Summary: 
Author: Rahul Salgare
Author-email: rahulsalgare@gofynd.com
Requires-Python: >=3.8,<4.0
Classifier: Programming Language :: Python :: 3
Classifier: Programming Language :: Python :: 3.10
Classifier: Programming Language :: Python :: 3.8
Classifier: Programming Language :: Python :: 3.9
Requires-Dist: pendulum (>=2.1.2,<3.0.0)
